[
    {
        "name": "Three Marks Coffee",
        "lat": 41.397168,
        "lng": 2.183123
    },
    {
        "name": "N\u00f8mad Roaster's Home",
        "lat": 41.397977,
        "lng": 2.195589
    },
    {
        "name": "Brew Coffee",
        "lat": 41.394562,
        "lng": 2.178425
    },
    {
        "name": "El Petit Pr\u00edncep",
        "lat": 41.396371,
        "lng": 2.177069
    },
    {
        "name": "Funky Bakers",
        "lat": 41.394916,
        "lng": 2.172866
    },
    {
        "name": "N\u00f8mad Coffee Lab & Shop",
        "lat": 41.388989,
        "lng": 2.177167
    },
    {
        "name": "Caf\u00e9s el Magn\u00edfico",
        "lat": 41.383541,
        "lng": 2.180957
    },
    {
        "name": "Federal",
        "lat": 41.399656,
        "lng": 2.205785
    },
    {
        "name": "El Born",
        "lat": 41.384704,
        "lng": 2.182978
    },
    {
        "name": "Bornet",
        "lat": 41.38483,
        "lng": 2.180255
    }
]